lrrr/__init__.py
lrrr/jupyter.py
lrrr/layout.py
lrrr/markdown.py
lrrr/utils.py
lrrr-0.2.0.dist-info/LICENSE
lrrr-0.2.0.dist-info/WHEEL
lrrr-0.2.0.dist-info/METADATA
lrrr-0.2.0.dist-info/RECORD
