Metadata-Version: 2.1
Name: lrrr
Version: 0.2.0
Summary: static website builder
Home-page: https://pypi.org/project/lrrr/
License: MIT
Keywords: webpage,jupyter,markdown
Author: walchko
Author-email: walchko@users.noreply.github.com
Requires-Python: >=3.6
Classifier: Development Status :: 4 - Beta
Classifier: Intended Audience :: Developers
Classifier: License :: OSI Approved :: MIT License
Classifier: Operating System :: OS Independent
Classifier: Programming Language :: Python :: 3
Classifier: Programming Language :: Python :: 3.6
Classifier: Programming Language :: Python :: 3.7
Classifier: Programming Language :: Python :: 3.8
Classifier: Programming Language :: Python :: 3.9
Classifier: Topic :: Software Development :: Libraries
Classifier: Topic :: Software Development :: Libraries :: Application Frameworks
Classifier: Topic :: Software Development :: Libraries :: Python Modules
Requires-Dist: importlib-metadata; python_version < "3.8"
Project-URL: Repository, https://github.com/nimbus-bp-1729/lrrr
